{
  "context": {
    "time": "2023-12-24T04:12:29.557221466+09:00",
    "query": "http://cal.syoboi.jp/db.php?Command=TitleLookup&LastUpdate=20231223_040000-20231224_040000&TID=%2A",
    "output": "/home/runner/work/syobocaldb/syobocaldb/2023/12/23.json"
  },
  "animes": [
    {
      "tid": 6510,
      "title": "アニメノウタ",
      "last_updated": "2023-12-23T13:04:17+09:00",
      "episodes": null,
      "songs": null,
      "staff": {},
      "cast": {
        "MC(#18～#60)": [
          "樋口楓"
        ],
        "MC(#1～#17)": [
          "ミライアカリ"
        ],
        "MC(#61～)": [
          "MindaRyn"
        ]
      }
    },
    {
      "tid": 6172,
      "title": "X年後の関係者たち ～あのムーブメントの舞台裏～",
      "last_updated": "2023-12-23T13:26:46+09:00",
      "episodes": null,
      "songs": null,
      "staff": {},
      "cast": {
        "MC": [
          "カズレーザー"
        ],
        "ナレーター": [
          "豊田綾乃"
        ]
      }
    },
    {
      "tid": 6865,
      "title": "僕らの雨いろプロトコル",
      "last_updated": "2023-12-23T14:09:40+09:00",
      "episodes": null,
      "songs": [
        {
          "title": "S9aiR",
          "label": "オープニング",
          "words": [
            "茜雫凛",
            "cAnON."
          ],
          "music": null,
          "composer": null,
          "singer": [
            "SennaRin"
          ],
          "anime": "僕らの雨いろプロトコル"
        },
        {
          "title": "Another Complex",
          "label": "エンディング",
          "words": null,
          "music": null,
          "composer": [
            "古川貴浩"
          ],
          "singer": null,
          "anime": "僕らの雨いろプロトコル"
        }
      ],
      "staff": {
        "アニメーション制作": [
          "Quad"
        ],
        "キャラクターデザイン": [
          "平山寛菜"
        ],
        "キャラクター原案": [
          "ぶーた"
        ],
        "シリーズ構成": [
          "高山カツヒコ",
          "山本靖貴"
        ],
        "ストーリー原案": [
          "兀兀"
        ],
        "プロップデザイン": [
          "監物ケビン雄太"
        ],
        "プロデュース": [
          "藍沢亮(スターリーキューブ)"
        ],
        "原作": [
          "Team KITSUNE"
        ],
        "撮影監督": [
          "今泉秀樹"
        ],
        "特殊効果": [
          "松田陵平"
        ],
        "監督": [
          "加藤大志"
        ],
        "総作画監督": [
          "森前和也"
        ],
        "総監督・音響監督": [
          "山本靖貴"
        ],
        "編集": [
          "増永純一"
        ],
        "美術": [
          "合六弘"
        ],
        "脚本": [
          "高山カツヒコ"
        ],
        "色彩設計": [
          "山上愛子"
        ],
        "製作": [
          "「ぼくあめ」製作委員会"
        ],
        "製作総指揮": [
          "夏目公一朗"
        ],
        "音楽": [
          "神前暁",
          "MONACA"
        ]
      },
      "cast": {
        "三枝悠宇": [
          "雨宮天"
        ],
        "仙堂暁斗": [
          "木村良平"
        ],
        "佐藤星詩流": [
          "本渡楓"
        ],
        "内嶋睦生": [
          "松岡禎丞"
        ],
        "小鳥遊恵美子": [
          "和氣あず未"
        ],
        "時野谷瞬": [
          "小野賢章"
        ],
        "時野谷美桜": [
          "麻倉もも"
        ],
        "稲月望": [
          "水瀬いのり"
        ],
        "長嶺流星": [
          "杉田智和"
        ]
      }
    },
    {
      "tid": 6819,
      "title": "ヒプノシスマイク -Division Rap Battle- Rhyme Anima ＋",
      "last_updated": "2023-12-23T14:10:35+09:00",
      "episodes": null,
      "songs": [
        {
          "title": "RISE FROM DEAD",
          "label": "オープニング",
          "words": [
            "invisible manners"
          ],
          "music": [
            "invisible manners"
          ],
          "composer": [
            "invisible manners"
          ],
          "singer": [
            "Division All Stars"
          ],
          "anime": "ヒプノシスマイク -Division Rap Battle- Rhyme Anima ＋"
        },
        {
          "title": "Next Stage -IKEBUKURO Ver.-",
          "label": "エンディング",
          "words": [
            "焚巻",
            "大蔵 from ケツメイシ"
          ],
          "music": null,
          "composer": null,
          "singer": [
            "Buster Bros!!!(山田一郎(木村昴)",
            "山田二郎(石谷春貴)",
            "山田三郎(天﨑滉平))"
          ],
          "anime": "ヒプノシスマイク -Division Rap Battle- Rhyme Anima ＋"
        },
        {
          "title": "Next Stage -YOKOHAMA Ver.-",
          "label": "エンディング",
          "words": [
            "FORK(ICE BAHN)",
            "玉露(ICE BAHN)",
            "KIT(ICE BAHN)",
            "大蔵 from ケツメイシ"
          ],
          "music": null,
          "composer": null,
          "singer": [
            "MAD TRIGGER CREW(碧棺左馬刻(浅沼晋太郎)",
            "入間銃兎(駒田航)",
            "毒島メイソン理鶯(神尾晋一郎))"
          ],
          "anime": "ヒプノシスマイク -Division Rap Battle- Rhyme Anima ＋"
        },
        {
          "title": "Next Stage -NAGOYA Ver.-",
          "label": "エンディング",
          "words": [
            "アフロ(MOROHA)",
            "大蔵 from ケツメイシ"
          ],
          "music": null,
          "composer": null,
          "singer": [
            "Bad Ass Temple(波羅夷空却(葉山翔太)",
            "四十物十四(榊原優希)",
            "天国獄(竹内栄治))"
          ],
          "anime": "ヒプノシスマイク -Division Rap Battle- Rhyme Anima ＋"
        },
        {
          "title": "Next Stage -OSAKA Ver.-",
          "label": "エンディング",
          "words": [
            "SHINGO★西成",
            "大蔵 from ケツメイシ"
          ],
          "music": null,
          "composer": null,
          "singer": [
            "どついたれ本舗(白膠木簓(岩崎諒太)",
            "躑躅森盧笙(河西健吾)",
            "天谷奴零(黒田崇矢))"
          ],
          "anime": "ヒプノシスマイク -Division Rap Battle- Rhyme Anima ＋"
        }
      ],
      "staff": {
        "CGディレクター": [
          "神田瑞帆"
        ],
        "キャラクターデザイン": [
          "芝美奈子",
          "森田莉奈"
        ],
        "シリーズ構成": [
          "吉田伸"
        ],
        "プロップデザイン": [
          "江間一隆"
        ],
        "制作": [
          "A-1 Pictures"
        ],
        "原作・音楽制作": [
          "EVIL LINE RECORDS"
        ],
        "撮影監督": [
          "宮脇洋平"
        ],
        "監督": [
          "小野勝巳"
        ],
        "総作画監督": [
          "森田莉奈",
          "落合瞳",
          "黒岩裕美"
        ],
        "編集": [
          "西村英一(タバック)"
        ],
        "美術監督": [
          "岡本綾乃(草薙)"
        ],
        "色彩設計": [
          "ホカリカナコ"
        ],
        "音楽": [
          "R・O・N"
        ],
        "音響制作": [
          "HALF H・P STUDIO"
        ],
        "音響監督": [
          "本山哲"
        ]
      },
      "cast": {
        "伊弉冉一二三": [
          "木島隆一"
        ],
        "入間銃兎": [
          "駒田航"
        ],
        "勘解由小路無花果": [
          "たかはし智秋"
        ],
        "四十物十四": [
          "榊原優希"
        ],
        "夢野幻太郎": [
          "斉藤壮馬"
        ],
        "天国獄": [
          "竹内栄治"
        ],
        "天谷奴零": [
          "黒田崇矢"
        ],
        "山田一郎": [
          "木村昴"
        ],
        "山田三郎": [
          "天﨑滉平"
        ],
        "山田二郎": [
          "石谷春貴"
        ],
        "有栖川帝統": [
          "野津山幸宏"
        ],
        "東方天乙統女": [
          "小林ゆう"
        ],
        "毒島メイソン理鶯": [
          "神尾晋一郎"
        ],
        "波羅夷空却": [
          "葉山翔太"
        ],
        "白膠木簓": [
          "岩崎諒太"
        ],
        "碧棺合歓": [
          "山本希望"
        ],
        "碧棺左馬刻": [
          "浅沼晋太郎"
        ],
        "神宮寺寂雷": [
          "速水奨"
        ],
        "観音坂独歩": [
          "伊東健人"
        ],
        "躑躅森盧笙": [
          "河西健吾"
        ],
        "飴村乱数": [
          "白井悠介"
        ]
      }
    },
    {
      "tid": 4152,
      "title": "ぼのぼの(2016)",
      "last_updated": "2023-12-23T18:53:13+09:00",
      "episodes": null,
      "songs": null,
      "staff": {
        "キャラクターデザイン": [
          "関口優花"
        ],
        "シリーズ構成": [
          "広田光毅"
        ],
        "プロデューサー": [
          "原大輔(フジテレビジョン)",
          "松下洋子"
        ],
        "作画協力": [
          "TYOアニメーションズ"
        ],
        "作画監督": [
          "根岸真知子",
          "関口優花"
        ],
        "制作": [
          "フジテレビ",
          "エイケン"
        ],
        "制作担当": [
          "貝田貴仁"
        ],
        "原作": [
          "いがらしみきお"
        ],
        "掲載誌": [
          "まんがライフ",
          "まんがくらぶ(竹書房)"
        ],
        "撮影監督": [
          "坂本裕一"
        ],
        "監督": [
          "山口秀憲"
        ],
        "美術監督": [
          "小日向乃理子"
        ],
        "色彩設計": [
          "千代間由佳"
        ],
        "音楽": [
          "若林タカツグ"
        ],
        "音響制作": [
          "グロービジョン"
        ],
        "音響効果": [
          "今野康之(スワラ・プロ)"
        ],
        "音響監督": [
          "横田知加子"
        ]
      },
      "cast": {
        "でっぷさん、テン助さん": [
          "中村悠一"
        ],
        "ぼのぼの": [
          "雪深山福子"
        ],
        "ぼのぼののおとうさん、イタチのおっさん": [
          "伊東孝明"
        ],
        "アナグマくん、ダイねえちゃん": [
          "あらいしずか"
        ],
        "アライグマ": [
          "高野慎平"
        ],
        "アライグマのおとうさん、トド": [
          "粟津貴嗣"
        ],
        "イケケさん": [
          "高木渉"
        ],
        "クズリ、ショーねえちゃん": [
          "重松朋"
        ],
        "シマリス": [
          "雄賀多あや"
        ],
        "シマリスくんのおにいさん": [
          "花江夏樹"
        ],
        "スナドリネコ、しまっちゃうおじさん": [
          "黒藤結軌"
        ],
        "ダイス": [
          "小野大輔"
        ],
        "ボボイさん": [
          "宮本充"
        ],
        "メイ、キラ": [
          "種﨑敦美"
        ],
        "ロッシ": [
          "神谷浩史"
        ]
      }
    },
    {
      "tid": 518,
      "title": "名探偵コナン",
      "last_updated": "2023-12-24T03:28:53+09:00",
      "episodes": null,
      "songs": null,
      "staff": {
        "アシスタントプロデューサー": [
          "斎藤朋之(よみうりテレビ)",
          "北田修一(よみうりテレビ)"
        ],
        "アソシエイトプロデューサー": [
          "浅井認"
        ],
        "キャラクターデザイン": [
          "須藤昌朋"
        ],
        "ストーリーエディター": [
          "飯岡順一"
        ],
        "チーフプロデューサー": [
          "諏訪道彦(よみうりテレビ)",
          "吉岡昌仁(東京ムービー)"
        ],
        "プロデューサー": [
          "小林弘明"
        ],
        "企画": [
          "諏訪道彦(よみうりテレビ)"
        ],
        "制作": [
          "よみうりテレビ",
          "東京ムービー"
        ],
        "制作担当": [
          "森脇誠"
        ],
        "原作": [
          "青山剛昌"
        ],
        "原案協力": [
          "都築伸一郎",
          "三上信一",
          "奥山豊彦",
          "鳥光裕"
        ],
        "広報": [
          "永井若菜(よみうりテレビ)",
          "藤本美歩(よみうりテレビ)"
        ],
        "掲載誌": [
          "週刊少年サンデー(小学館)"
        ],
        "撮影監督": [
          "小川隆久"
        ],
        "監督": [
          "佐藤真人"
        ],
        "編集": [
          "岡田輝満"
        ],
        "美術監督": [
          "光元博行"
        ],
        "色彩設計": [
          "中尾総子"
        ],
        "音楽": [
          "大野克夫"
        ],
        "音響監督": [
          "浦上靖夫",
          "井澤基"
        ]
      },
      "cast": {
        "ウォッカ": [
          "立木文彦"
        ],
        "ジン": [
          "堀之紀"
        ],
        "佐藤刑事": [
          "湯屋敦子"
        ],
        "元太・高木刑事": [
          "高木渉"
        ],
        "光彦": [
          "大谷育江"
        ],
        "千葉刑事": [
          "千葉一伸"
        ],
        "妃 英理": [
          "高島雅羅"
        ],
        "工藤優作": [
          "田中秀幸"
        ],
        "工藤新一": [
          "山口勝平"
        ],
        "工藤有希子": [
          "島本須美"
        ],
        "服部平次": [
          "堀川りょう"
        ],
        "歩美": [
          "岩居由希子"
        ],
        "毛利 蘭": [
          "山崎和佳奈"
        ],
        "毛利小五郎": [
          "神谷明(#1～#552)",
          "小山力也(#553～)"
        ],
        "江戸川コナン": [
          "高山みなみ"
        ],
        "灰原 哀": [
          "林原めぐみ"
        ],
        "白鳥警部": [
          "井上和彦"
        ],
        "目暮警部": [
          "茶風林"
        ],
        "遠山和葉": [
          "宮村優子"
        ],
        "鈴木園子": [
          "松井菜桜子"
        ],
        "阿笠博士": [
          "緒方賢一"
        ]
      }
    },
    {
      "tid": 6778,
      "title": "シャドウバースF(セブンシャドウズ編)",
      "last_updated": "2023-12-24T05:23:42+09:00",
      "episodes": null,
      "songs": [
        {
          "title": "灯火",
          "label": "オープニング",
          "words": null,
          "music": null,
          "composer": [
            "Naoki Itai",
            "Half time Old"
          ],
          "singer": [
            "Half time Old"
          ],
          "anime": "シャドウバースF(セブンシャドウズ編)"
        },
        {
          "title": "シェケナーレ",
          "label": "エンディング",
          "words": [
            "児玉雨子"
          ],
          "music": [
            "ANDW"
          ],
          "composer": [
            "中村瑛彦"
          ],
          "singer": [
            "OCHA NORMA"
          ],
          "anime": "シャドウバースF(セブンシャドウズ編)"
        }
      ],
      "staff": {
        "3DCGディレクター": [
          "神谷貴浩"
        ],
        "アニメーション制作": [
          "ZEXCS"
        ],
        "アートディレクター": [
          "ぽんず"
        ],
        "キャラクターデザイン": [
          "原田大基"
        ],
        "キャラクター原案": [
          "岡田学彌",
          "みけぼし",
          "ヘスン",
          "おにねこ",
          "ねじ太"
        ],
        "サブキャラクターデザイン": [
          "新田靖成"
        ],
        "シリーズ構成": [
          "磯崎輪太郎",
          "赤尾でこ",
          "川口敬一郎"
        ],
        "デジフレデザイン": [
          "宮川知子"
        ],
        "フォロワー監督": [
          "北川大輔"
        ],
        "プロップデザイン": [
          "岩永悦宜"
        ],
        "モニターグラフィックス": [
          "sankaku"
        ],
        "副監督": [
          "林直孝"
        ],
        "原作": [
          "Cygames"
        ],
        "撮影監督": [
          "中村雄太",
          "木村康史",
          "木船颯人"
        ],
        "監督": [
          "川口敬一郎"
        ],
        "編集": [
          "平木大輔"
        ],
        "美術監督": [
          "伊藤大樹"
        ],
        "美術設定": [
          "緒川マミオ"
        ],
        "色彩設計": [
          "佐藤直子",
          "品地奈々絵"
        ],
        "製作": [
          "テレビ東京",
          "アニメ「シャドウバースF」製作委員会"
        ],
        "音楽": [
          "池頼広"
        ],
        "音響制作": [
          "ソニルード"
        ],
        "音響監督": [
          "飯田里樹"
        ]
      },
      "cast": {
        "ジェントルマン": [
          "森久保祥太郎"
        ],
        "ドラグニル": [
          "井澤詩織"
        ],
        "乙坂シオン": [
          "集貝はな"
        ],
        "天竜ライト": [
          "上村祐翔"
        ],
        "小鳥遊ツバサ": [
          "富田美憂"
        ],
        "白銀ミカド": [
          "榊原優希"
        ],
        "真壁スバル": [
          "浦和希"
        ],
        "蜜田川イツキ": [
          "山村響"
        ],
        "邪星リョウガ": [
          "逢坂良太"
        ],
        "風祭レン": [
          "武田羅梨沙多胡"
        ]
      }
    },
    {
      "tid": 6954,
      "title": "マヂカルラブリーの全力！アニシャド応援部2",
      "last_updated": "2023-12-24T05:24:12+09:00",
      "episodes": null,
      "songs": null,
      "staff": {},
      "cast": {
        "ドラグニル": [
          "井澤詩織"
        ],
        "出演": [
          "村上(マヂカルラブリー)",
          "野田クリスタル(マヂカルラブリー)"
        ]
      }
    },
    {
      "tid": 6955,
      "title": "頭文字D Fifth Stage",
      "last_updated": "2023-12-24T06:48:50+09:00",
      "episodes": null,
      "songs": [
        {
          "title": "Raise Up",
          "label": "オープニング",
          "words": null,
          "music": null,
          "composer": null,
          "singer": [
            "m.o.v.e"
          ],
          "anime": "頭文字D Fifth Stage"
        },
        {
          "title": "Flyleaf",
          "label": "エンディング",
          "words": null,
          "music": null,
          "composer": null,
          "singer": [
            "CLUTCHO"
          ],
          "anime": "頭文字D Fifth Stage"
        },
        {
          "title": "夕愁想花",
          "label": "エンディング",
          "words": null,
          "music": null,
          "composer": null,
          "singer": [
            "m.o.v.e"
          ],
          "anime": "頭文字D Fifth Stage"
        }
      ],
      "staff": {
        "CG監督": [
          "安田兼盛"
        ],
        "アニメーション制作": [
          "シナジーSP"
        ],
        "キャラクターデザイン": [
          "佐藤正樹"
        ],
        "メカニックデザイン": [
          "横井秀章"
        ],
        "原作": [
          "しげの秀一(講談社「ヤングマガジン」掲載)"
        ],
        "監修": [
          "土屋圭市",
          "ホットバージョン"
        ],
        "監督": [
          "橋本みつお"
        ],
        "美術監督": [
          "坂本信人"
        ],
        "脚本": [
          "岸間信明"
        ],
        "製作": [
          "ウェッジリンク"
        ],
        "音楽": [
          "梅堀淳"
        ],
        "音響監督": [
          "三間雅文"
        ]
      },
      "cast": {
        "ケンタ": [
          "岡野浩介"
        ],
        "上原美佳": [
          "早見沙織"
        ],
        "久保英次": [
          "加藤康之"
        ],
        "健二": [
          "高木渉"
        ],
        "北条凛": [
          "中村悠一"
        ],
        "北条豪": [
          "木内秀信"
        ],
        "史浩": [
          "細井治"
        ],
        "大宮智史": [
          "東地宏樹"
        ],
        "奥山広也": [
          "阪口周平"
        ],
        "小早川": [
          "浜田賢二"
        ],
        "小柏カイ": [
          "神奈延年"
        ],
        "武内樹": [
          "岩田光央"
        ],
        "池田竜次": [
          "中井和哉"
        ],
        "池谷浩一郎": [
          "矢尾一樹"
        ],
        "皆川英雄": [
          "小西克幸"
        ],
        "藤原拓海": [
          "三木眞一郎"
        ],
        "藤原文太": [
          "石塚運昇"
        ],
        "香織": [
          "遠藤綾"
        ],
        "高橋啓介": [
          "関智一"
        ],
        "高橋涼介": [
          "子安武人"
        ]
      }
    },
    {
      "tid": 6825,
      "title": "ひきこまり吸血姫の悶々",
      "last_updated": "2023-12-24T07:43:41+09:00",
      "episodes": null,
      "songs": [
        {
          "title": "Red Liberation",
          "label": "オープニング",
          "words": null,
          "music": null,
          "composer": [
            "八木沼悟志",
            "齋藤真也"
          ],
          "singer": [
            "fripSide"
          ],
          "anime": "ひきこまり吸血姫の悶々"
        },
        {
          "title": "眠れない feat.楠木ともり",
          "label": "エンディング",
          "words": null,
          "music": null,
          "composer": null,
          "singer": null,
          "anime": "ひきこまり吸血姫の悶々"
        }
      ],
      "staff": {
        "3DCG監督": [
          "濱村敏郎(ワイヤード)"
        ],
        "アクションディレクター": [
          "髙木啓明"
        ],
        "アニメーション制作": [
          "project No.9"
        ],
        "キャスティングマネージャー": [
          "泊一平"
        ],
        "キャラクターデザイン": [
          "下谷智之"
        ],
        "キャラクター原案": [
          "りいちゅ"
        ],
        "サブキャラクターデザイン": [
          "倉橋N濘",
          "阿見圭之介"
        ],
        "シリーズ構成・脚本": [
          "大知慶一郎"
        ],
        "プロップデザイン": [
          "髙木あゆみ"
        ],
        "原作": [
          "小林湖底(GA文庫)"
        ],
        "撮影監督": [
          "上條智也(project No.9)"
        ],
        "監督": [
          "南川達馬"
        ],
        "編集": [
          "丹彩子"
        ],
        "美術監督": [
          "葛琳"
        ],
        "美術設定": [
          "高橋麻穂"
        ],
        "色彩設計": [
          "林由稀"
        ],
        "製作": [
          "ひきこまり製作委員会"
        ],
        "音楽": [
          "椎名豪"
        ],
        "音楽制作": [
          "DMM.com"
        ],
        "音響制作": [
          "ビットグルーヴプロモーション"
        ],
        "音響効果": [
          "今野康之"
        ],
        "音響監督": [
          "高橋剛"
        ]
      },
      "cast": {
        "アバークロンビー": [
          "中村源太"
        ],
        "アマツ・カクメイ": [
          "中村悠一"
        ],
        "アマツ・カルラ": [
          "島袋美由利"
        ],
        "アルマン・ガンデスブラッド": [
          "福島潤"
        ],
        "オディロン・メタル": [
          "稲田徹"
        ],
        "カオステル・コント": [
          "花江夏樹"
        ],
        "カレン・エルヴェシアス": [
          "日笠陽子"
        ],
        "ガートルード": [
          "日高里菜"
        ],
        "コルネリウス": [
          "いなせあおい"
        ],
        "サクナ・メモワール": [
          "石見舞菜香"
        ],
        "ティオ・フラット": [
          "水野朔"
        ],
        "テラコマリ・ガンデスブラッド": [
          "楠木ともり"
        ],
        "デルピュネー": [
          "藤原夏海"
        ],
        "ネリア・カニンガム": [
          "ファイルーズあい"
        ],
        "ネルソン": [
          "柳田淳一"
        ],
        "バシュラール": [
          "坂田将吾"
        ],
        "フレーテ・マスカレール": [
          "杉山里穂"
        ],
        "ブーケファロス": [
          "魚建"
        ],
        "プロヘリヤ・ズタズタスキー": [
          "悠木碧"
        ],
        "ヘルデウス・ヘブン": [
          "宇垣秀成"
        ],
        "ベリウス・イッヌ・ケルベロ": [
          "水中雅章"
        ],
        "マッドハルト": [
          "井上和彦"
        ],
        "ミリセント・ブルーナイト": [
          "雨宮天"
        ],
        "メアリ": [
          "上田瞳"
        ],
        "メラコンシー": [
          "畠中祐"
        ],
        "メルカ・ティアーノ": [
          "上田麗奈"
        ],
        "ユーリン・ガンデスブラッド": [
          "川澄綾子"
        ],
        "ヨハン・ヘルダース": [
          "小林裕介"
        ],
        "レインズワース": [
          "岡本信彦"
        ],
        "ヴィルヘイズ": [
          "鈴代紗弓"
        ],
        "実況": [
          "関根明良"
        ],
        "峰永こはる": [
          "木野日菜"
        ]
      }
    },
    {
      "tid": 6858,
      "title": "SPY×FAMILY Season 2",
      "last_updated": "2023-12-24T08:58:40+09:00",
      "episodes": null,
      "songs": [
        {
          "title": "クラクラ",
          "label": "オープニング",
          "words": null,
          "music": null,
          "composer": null,
          "singer": [
            "Ado"
          ],
          "anime": "SPY×FAMILY Season 2"
        },
        {
          "title": "トドメの一撃 feat.Cory Wong",
          "label": "エンディング",
          "words": null,
          "music": null,
          "composer": null,
          "singer": null,
          "anime": "SPY×FAMILY Season 2"
        },
        {
          "title": "Little steps",
          "label": "挿入歌",
          "words": null,
          "music": null,
          "composer": null,
          "singer": null,
          "anime": "SPY×FAMILY Season 2"
        },
        {
          "title": "Until the End",
          "label": "挿入歌",
          "words": null,
          "music": null,
          "composer": null,
          "singer": null,
          "anime": "SPY×FAMILY Season 2"
        },
        {
          "title": "uneven fruit",
          "label": "挿入歌",
          "words": null,
          "music": null,
          "composer": null,
          "singer": null,
          "anime": "SPY×FAMILY Season 2"
        }
      ],
      "staff": {
        "3DCG監督": [
          "宮地克明"
        ],
        "キャラクターデザイン・総作画監督": [
          "嶋田和晃"
        ],
        "シリーズ構成": [
          "大河内一楼"
        ],
        "制作": [
          "WIT STUDIO",
          "CloverWorks"
        ],
        "副シリーズ構成": [
          "谷村大四郎",
          "久尾歩"
        ],
        "原作": [
          "遠藤達哉"
        ],
        "掲載誌": [
          "少年ジャンプ＋(集英社)"
        ],
        "撮影監督": [
          "佐久間悠也"
        ],
        "監督": [
          "古橋一浩",
          "原田孝宏"
        ],
        "編集": [
          "齋藤朱里(三嶋編集室)"
        ],
        "美術監督": [
          "臼井みなみ"
        ],
        "美術設定": [
          "塩澤良憲",
          "スタジオイースター"
        ],
        "色彩設計": [
          "原恭子"
        ],
        "製作": [
          "「SPY×FAMILY」製作委員会"
        ],
        "音楽プロデュース": [
          "(K)NoW_NAME"
        ],
        "音響効果": [
          "出雲範子"
        ],
        "音響監督": [
          "はたしょう二"
        ]
      },
      "cast": {
        "〈ガーデン〉店長": [
          "諏訪部順一"
        ],
        "アーニャ・フォージャー": [
          "種﨑敦美"
        ],
        "オルカ・グレッチャー": [
          "遠藤綾"
        ],
        "グラム・グレッチャー": [
          "大井麻利衣"
        ],
        "シルヴィア・シャーウッド": [
          "甲斐田裕子"
        ],
        "ダミアン・デズモンド": [
          "藤原夏海"
        ],
        "ナレーション": [
          "松田健一郎"
        ],
        "ファーシル・グレイ": [
          "寺島惇太"
        ],
        "フィオナ・フロスト": [
          "佐倉綾音"
        ],
        "フランキー・フランクリン": [
          "吉野裕行"
        ],
        "ヘンリー・ヘンダーソン": [
          "山路和弘"
        ],
        "ベッキー・ブラックベル": [
          "加藤英美里"
        ],
        "ボンド・フォージャー": [
          "松田健一郎"
        ],
        "マシュー・マクマホン": [
          "堀内賢雄"
        ],
        "ユーリ・ブライア": [
          "小野賢章"
        ],
        "ヨル・フォージャー": [
          "早見沙織"
        ],
        "ロイド・フォージャー": [
          "江口拓也"
        ]
      }
    },
    {
      "tid": 6824,
      "title": "最果てのパラディン 鉄錆の山の王",
      "last_updated": "2023-12-24T10:06:30+09:00",
      "episodes": null,
      "songs": [
        {
          "title": "命火",
          "label": "オープニング",
          "words": null,
          "music": null,
          "composer": null,
          "singer": null,
          "anime": "最果てのパラディン 鉄錆の山の王"
        },
        {
          "title": "パズル",
          "label": "エンディング",
          "words": [
            "amazuti"
          ],
          "music": [
            "amazuti"
          ],
          "composer": [
            "amazuti"
          ],
          "singer": [
            "KOTOKO"
          ],
          "anime": "最果てのパラディン 鉄錆の山の王"
        },
        {
          "title": "竜殺しの英雄の歌",
          "label": "エンディング",
          "words": [
            "柳野かなた"
          ],
          "music": null,
          "composer": null,
          "singer": [
            "ロビィナ・グッドフェロー(鈴木絵理)"
          ],
          "anime": "最果てのパラディン 鉄錆の山の王"
        }
      ],
      "staff": {
        "2DCGディレクター": [
          "中野剛"
        ],
        "3DCGアニメーションディレクター": [
          "鈴木雅臣"
        ],
        "アニメーション制作": [
          "OLM",
          "SUNRISE BEYOND"
        ],
        "キャラクターデザイン": [
          "新井達也",
          "羽田浩二"
        ],
        "キャラクター原案": [
          "輪くすさが"
        ],
        "シリーズ構成": [
          "髙橋龍也"
        ],
        "プロデュース": [
          "グッドスマイルフィルム"
        ],
        "メインアニメーター": [
          "高見明男",
          "石原満",
          "黒澤浩美"
        ],
        "モンスターデザイン": [
          "江禹辰"
        ],
        "原作": [
          "柳野かなた(オーバーラップ文庫)"
        ],
        "撮影監督": [
          "口羽毅"
        ],
        "監督": [
          "岩永彰"
        ],
        "編集": [
          "後田良樹"
        ],
        "美術監督": [
          "楊澤辰(Children's Playground Entertainment)"
        ],
        "色彩設計": [
          "のぼりはるこ"
        ],
        "製作": [
          "最果てのパラディン製作委員会(bilibili",
          "オーバーラップ",
          "ドコモ・アニメストア",
          "OLM)"
        ],
        "音楽": [
          "高田龍一(MONACA)",
          "帆足圭吾(MONACA)"
        ],
        "音響制作": [
          "ダックスプロダクション"
        ],
        "音響監督": [
          "八木沼智彦"
        ]
      },
      "cast": {
        "ウィル": [
          "千葉翔也"
        ],
        "エセルバルド": [
          "田丸篤志"
        ],
        "ガス": [
          "飛田展男"
        ],
        "グレイスフィール": [
          "悠木碧"
        ],
        "ゲルレイズ": [
          "松田健一郎"
        ],
        "トニオ": [
          "遊佐浩二"
        ],
        "バグリー": [
          "稲葉実"
        ],
        "ビィ": [
          "鈴木絵理"
        ],
        "ブラッド": [
          "小西克幸"
        ],
        "マリー": [
          "堀江由衣"
        ],
        "メネル": [
          "村瀬歩"
        ],
        "ルゥ": [
          "四宮豪"
        ],
        "レイストフ": [
          "乃村健次"
        ],
        "幼少期・少年期ウィル": [
          "河瀬茉希"
        ]
      }
    },
    {
      "tid": 6841,
      "title": "豚のレバーは加熱しろ",
      "last_updated": "2023-12-24T10:10:15+09:00",
      "episodes": null,
      "songs": [
        {
          "title": "私が笑う理由は",
          "label": "オープニング",
          "words": null,
          "music": null,
          "composer": null,
          "singer": null,
          "anime": "豚のレバーは加熱しろ"
        },
        {
          "title": "ひとりじゃないよ",
          "label": "エンディング",
          "words": null,
          "music": [
            "山口寛雄"
          ],
          "composer": [
            "大久保友裕"
          ],
          "singer": null,
          "anime": "豚のレバーは加熱しろ"
        }
      ],
      "staff": {
        "CGディレクター・2D": [
          "濱村敏郎(ワイヤード)"
        ],
        "アニメーション制作": [
          "project No.9"
        ],
        "キャラクターデザイン": [
          "渡辺奏"
        ],
        "サブキャラクターデザイン": [
          "倉橋N濘"
        ],
        "シリーズ構成": [
          "赤尾でこ"
        ],
        "プロップデザイン": [
          "ヒラタリョウ"
        ],
        "原作": [
          "逆井卓馬(電撃文庫)"
        ],
        "原作イラスト": [
          "遠坂あさぎ"
        ],
        "撮影監督": [
          "杉山大樹(project No.9)"
        ],
        "監督": [
          "高橋雅之"
        ],
        "編集": [
          "丹彩子"
        ],
        "美術設定・美術監督": [
          "中村嘉博(デザインオフィスメカマン)"
        ],
        "色彩設計": [
          "吉里修耶"
        ],
        "製作": [
          "アニプレックス",
          "KADOKAWA",
          "BS11"
        ],
        "音楽": [
          "末廣健一郎",
          "MAYUKO"
        ],
        "音楽制作": [
          "アニプレックス"
        ],
        "音響監督": [
          "立石弥生"
        ]
      },
      "cast": {
        "ジェス": [
          "楠木ともり"
        ],
        "セレス": [
          "富田美憂"
        ],
        "ノット": [
          "伊東健人"
        ],
        "ブレース": [
          "能登麻美子"
        ],
        "豚": [
          "松岡禎丞"
        ]
      }
    },
    {
      "tid": 6805,
      "title": "シャングリラ・フロンティア～クソゲーハンター、神ゲーに挑まんとす～",
      "last_updated": "2023-12-24T10:16:18+09:00",
      "episodes": null,
      "songs": [
        {
          "title": "BROKEN GAMES",
          "label": "オープニング",
          "words": null,
          "music": null,
          "composer": [
            "HONNWAKA88"
          ],
          "singer": [
            "FZMZ"
          ],
          "anime": "シャングリラ・フロンティア～クソゲーハンター、神ゲーに挑まんとす～"
        },
        {
          "title": "エース",
          "label": "エンディング",
          "words": null,
          "music": null,
          "composer": [
            "tepe"
          ],
          "singer": [
            "CHiCO"
          ],
          "anime": "シャングリラ・フロンティア～クソゲーハンター、神ゲーに挑まんとす～"
        }
      ],
      "staff": {
        "2Dワークス": [
          "田村あず紗"
        ],
        "3Dデザイン": [
          "Emotional Pictures　"
        ],
        "アクションディレクター・エフェクトディレクター": [
          "酒井智史"
        ],
        "アクション作画監督": [
          "日浦玲奈",
          "星野玲香"
        ],
        "アニメーション制作": [
          "C2C"
        ],
        "キャラクターデザイン・総作画監督": [
          "倉島亜由美"
        ],
        "シリーズ構成・脚本": [
          "筆安一幸"
        ],
        "プロップデザイン": [
          "横山友紀",
          "河野絵美"
        ],
        "メインアニメーター": [
          "芳賀亮",
          "月田文律",
          "西野武志",
          "姚江浩",
          "新田駿也"
        ],
        "モンスターデザイン": [
          "長森佳容",
          "大河広行",
          "河野絵美",
          "有澤寛"
        ],
        "副監督": [
          "池下博紀"
        ],
        "原作": [
          "硬梨菜",
          "不二涼介"
        ],
        "掲載誌": [
          "週刊少年マガジン(講談社)"
        ],
        "撮影監督": [
          "山杢光"
        ],
        "監督": [
          "窪岡俊之"
        ],
        "総動画監修": [
          "髙橋知也"
        ],
        "編集": [
          "定松剛"
        ],
        "美術アドバイザー": [
          "増山修"
        ],
        "美術監督": [
          "野辺勇紀(インスパイアード)",
          "中村朝咲(インスパイアード)"
        ],
        "色彩設計": [
          "高木雅人"
        ],
        "色彩設計補佐": [
          "手倉森咲子"
        ],
        "音楽": [
          "髙田龍一(MONACA)",
          "広川恵一(MONACA)",
          "高橋邦幸(MONACA)"
        ],
        "音響監督": [
          "藤田亜紀子"
        ]
      },
      "cast": {
        "Animalia": [
          "千本木彩花"
        ],
        "アーサー・ペンシルゴン／天音永遠": [
          "日笠陽子"
        ],
        "エムル": [
          "日高里菜"
        ],
        "オイカッツォ／魚臣慧": [
          "小市眞琴"
        ],
        "オルスロット": [
          "山下誠一郎"
        ],
        "サイガ-0／斎賀玲": [
          "和氣あず未"
        ],
        "サイガ-100": [
          "花守ゆみり"
        ],
        "サンラク／陽務楽郎": [
          "内田雄馬"
        ],
        "ピーツ": [
          "松田颯水"
        ],
        "ヴァイスアッシュ": [
          "大塚明夫"
        ]
      }
    },
    {
      "tid": 6867,
      "title": "ドッグシグナル",
      "last_updated": "2023-12-24T10:28:15+09:00",
      "episodes": null,
      "songs": [
        {
          "title": "雪月風花",
          "label": "オープニング",
          "words": null,
          "music": null,
          "composer": [
            "鈴木Daichi秀行"
          ],
          "singer": null,
          "anime": "ドッグシグナル"
        },
        {
          "title": "シュガースポット",
          "label": "エンディング",
          "words": null,
          "music": null,
          "composer": [
            "knoak"
          ],
          "singer": null,
          "anime": "ドッグシグナル"
        }
      ],
      "staff": {
        "アニメーション制作": [
          "冨嶽"
        ],
        "制作": [
          "NHKエンタープライズ"
        ],
        "制作・著作": [
          "NHK"
        ],
        "原作": [
          "みやうち沙矢"
        ],
        "監督・シリーズ構成": [
          "古橋一浩"
        ],
        "脚本": [
          "芦野里美"
        ],
        "音楽": [
          "大島ミチル"
        ],
        "音響監督": [
          "吉田光平"
        ]
      },
      "cast": {
        "ウルソン": [
          "松田健一郎"
        ],
        "サンジュ": [
          "麦穂あんな"
        ],
        "丹羽眞一郎": [
          "鈴村健一"
        ],
        "久宝鈴之介": [
          "KENN"
        ],
        "佐村未祐": [
          "小野賢章"
        ],
        "優子": [
          "伊瀬茉莉也"
        ],
        "泉律佳": [
          "甲斐田裕子"
        ]
      }
    },
    {
      "tid": 6793,
      "title": "薬屋のひとりごと",
      "last_updated": "2023-12-24T10:29:31+09:00",
      "episodes": null,
      "songs": [
        {
          "title": "花になって",
          "label": "オープニング",
          "words": [
            "長屋晴子"
          ],
          "music": [
            "穴見真吾"
          ],
          "composer": [
            "川口圭太",
            "穴見真吾"
          ],
          "singer": [
            "緑黄色社会"
          ],
          "anime": "薬屋のひとりごと"
        },
        {
          "title": "アイコトバ",
          "label": "エンディング",
          "words": null,
          "music": null,
          "composer": [
            "トオミヨウ"
          ],
          "singer": [
            "アイナ・ジ・エンド"
          ],
          "anime": "薬屋のひとりごと"
        },
        {
          "title": "想風",
          "label": "挿入歌",
          "words": null,
          "music": null,
          "composer": null,
          "singer": null,
          "anime": "薬屋のひとりごと"
        },
        {
          "title": "明日を訪ねて",
          "label": "挿入歌",
          "words": null,
          "music": null,
          "composer": null,
          "singer": null,
          "anime": "薬屋のひとりごと"
        },
        {
          "title": "雪中花",
          "label": "挿入歌",
          "words": [
            "内田ましろ"
          ],
          "music": [
            "神前暁"
          ],
          "composer": null,
          "singer": [
            "きしかな子"
          ],
          "anime": "薬屋のひとりごと"
        }
      ],
      "staff": {
        "2Dデザインワークス": [
          "南條楊輔"
        ],
        "CGIディレクター": [
          "永井有"
        ],
        "アニメーション制作": [
          "TOHO animation STUDIO",
          "OLM"
        ],
        "キャラクターデザイン": [
          "中谷友紀子"
        ],
        "キャラクター原案": [
          "しのとうこ"
        ],
        "サブキャラクターデザイン": [
          "長森佳容",
          "宮井加奈"
        ],
        "シナリオ統括": [
          "柿原優子"
        ],
        "プロップデザイン": [
          "ヒラタリョウ",
          "みき尾"
        ],
        "副監督": [
          "筆坂明規"
        ],
        "原作": [
          "日向夏(ヒーロー文庫)"
        ],
        "撮影監督": [
          "石黒瑠美(T2 studio)"
        ],
        "監督・シリーズ構成": [
          "長沼範裕"
        ],
        "編集": [
          "今井大介"
        ],
        "美術監督": [
          "髙尾克己"
        ],
        "色彩設計": [
          "相田美里"
        ],
        "製作": [
          "「薬屋のひとりごと」製作委員会"
        ],
        "音楽": [
          "神前暁",
          "Kevin Penkin",
          "桶狭間ありさ"
        ],
        "音響効果": [
          "出雲範子"
        ],
        "音響監督": [
          "はたしょう二"
        ]
      },
      "cast": {
        "やぶ医者": [
          "かぬか光明"
        ],
        "やり手婆": [
          "斉藤貴美子"
        ],
        "ナレーション": [
          "島本須美"
        ],
        "壬氏": [
          "大塚剛央"
        ],
        "女華": [
          "七海ひろき"
        ],
        "小蘭": [
          "久野美咲"
        ],
        "李白": [
          "赤羽根健治"
        ],
        "梅梅": [
          "潘めぐみ"
        ],
        "梨花妃": [
          "石川由依"
        ],
        "猫猫": [
          "悠木碧"
        ],
        "玉葉妃": [
          "種﨑敦美"
        ],
        "白鈴": [
          "小清水亜美"
        ],
        "羅門": [
          "家中宏"
        ],
        "里樹妃": [
          "木野日菜"
        ],
        "阿多妃": [
          "甲斐田裕子"
        ],
        "高順": [
          "小西克幸"
        ]
      }
    },
    {
      "tid": 6838,
      "title": "オチビサン",
      "last_updated": "2023-12-24T10:31:22+09:00",
      "episodes": null,
      "songs": null,
      "staff": {
        "3Dキャラクターモデリング": [
          "若月薪太郎",
          "山内研",
          "鈴木貴志",
          "齋藤弘光"
        ],
        "CGアニメーションディレクター": [
          "石川将輝",
          "山内智史",
          "給田洋"
        ],
        "シリーズ構成・脚本・アニメーション制作": [
          "スタジオカラー"
        ],
        "制作・著作": [
          "NHK",
          "豆粒町内会"
        ],
        "効果": [
          "野崎博樹"
        ],
        "原作": [
          "安野モヨコ"
        ],
        "撮影監督": [
          "酒井淳子"
        ],
        "演出": [
          "吉邉尚希",
          "新子太一",
          "小林彩",
          "どろみず"
        ],
        "監督": [
          "鬼塚大輔",
          "釣井省吾"
        ],
        "編集": [
          "木村佳史子"
        ],
        "美術監督": [
          "矢口聖奈"
        ],
        "色彩設計": [
          "平塚のぞみ"
        ],
        "録音": [
          "鶴巻慶典"
        ],
        "音楽": [
          "神前暁"
        ],
        "音響監督": [
          "山田陽"
        ]
      },
      "cast": {
        "おじい": [
          "茶風林"
        ],
        "アカメちゃん": [
          "小倉唯"
        ],
        "オチビサン": [
          "塙真奈美"
        ],
        "シロッポイ": [
          "久野美咲"
        ],
        "ジャック": [
          "後藤ヒロキ"
        ],
        "ナゼニ": [
          "岡本信彦"
        ],
        "パンくい": [
          "井澤詩織"
        ],
        "ヘビくん": [
          "越後屋コースケ"
        ]
      }
    },
    {
      "tid": 6839,
      "title": "ゴブリンスレイヤーⅡ",
      "last_updated": "2023-12-24T10:31:28+09:00",
      "episodes": null,
      "songs": [
        {
          "title": "Entertainment",
          "label": "オープニング",
          "words": [
            "Cassie Wei"
          ],
          "music": [
            "Cassie Wei",
            "Yamato Kasai"
          ],
          "composer": [
            "Yamato Kasai",
            "arai tasuku"
          ],
          "singer": [
            "Mili"
          ],
          "anime": "ゴブリンスレイヤーⅡ"
        },
        {
          "title": "霞の向こうへ",
          "label": "エンディング",
          "words": null,
          "music": null,
          "composer": [
            "amazuti"
          ],
          "singer": [
            "中島由貴"
          ],
          "anime": "ゴブリンスレイヤーⅡ"
        }
      ],
      "staff": {
        "アニメーション制作": [
          "ライデンフィルム"
        ],
        "エフェクトデザイン": [
          "小田裕康"
        ],
        "キャラクターデザイン": [
          "加藤裕美"
        ],
        "キャラクター原案": [
          "神奈月昇"
        ],
        "サブキャラクターデザイン": [
          "寺尾憲治",
          "服部聰志"
        ],
        "シリーズ構成・脚本": [
          "倉田英之"
        ],
        "デザインワークス": [
          "渡部岳",
          "中島俊",
          "二川大"
        ],
        "プロップデザイン": [
          "服部聰志"
        ],
        "モンスターデザイン": [
          "小澤理彦"
        ],
        "原作": [
          "蝸牛くも(GA文庫)"
        ],
        "撮影監督": [
          "野澤圭輔"
        ],
        "特効監修": [
          "谷口久美子"
        ],
        "特殊効果": [
          "チーム・タニグチ",
          "荒畑歩美"
        ],
        "監督": [
          "髙田美里"
        ],
        "総監督": [
          "尾崎隆晴"
        ],
        "編集": [
          "エディッツ",
          "梅津朋美"
        ],
        "美術監督": [
          "甲斐政俊"
        ],
        "美術設定": [
          "SAKO",
          "李書九",
          "高橋大地"
        ],
        "色彩設計": [
          "野地弘納"
        ],
        "衣装デザイン": [
          "寺尾憲治"
        ],
        "製作": [
          "ゴブリンスレイヤーⅡ製作委員会(博報堂DYミュージック＆ピクチャーズ",
          "SBクリエイティブ",
          "グッドスマイルフィルム",
          "ソニー・ピクチャーズエンタテインメント",
          "ブシロード",
          "エー・ティー・エックス",
          "フロンティアワークス)"
        ],
        "音楽": [
          "末廣健一郎"
        ],
        "音楽制作": [
          "グッドスマイルフィルム",
          "アーティスト・マネージメント・オフィス"
        ],
        "音楽制作協力": [
          "ワンミュージック"
        ],
        "音響制作": [
          "マジックカプセル"
        ],
        "音響効果": [
          "古谷友二(スワラ・プロ)"
        ],
        "音響監督": [
          "濱野高年"
        ]
      },
      "cast": {
        "ゴブリンスレイヤー": [
          "梅原裕一郎"
        ],
        "ゴブリンスレイヤーの幼少期": [
          "松田颯水"
        ],
        "使用人": [
          "中村カンナ"
        ],
        "侍女": [
          "長谷川育美"
        ],
        "侍祭": [
          "杉山里穂"
        ],
        "剣の乙女": [
          "遠藤綾"
        ],
        "剣士": [
          "内匠靖明"
        ],
        "剣聖": [
          "戸松遥"
        ],
        "勇者": [
          "島袋美由利"
        ],
        "半森人斥候": [
          "福島潤"
        ],
        "受付嬢": [
          "内田真礼"
        ],
        "国王": [
          "三木眞一郎"
        ],
        "圃人": [
          "飛田展男"
        ],
        "圃人剣士": [
          "鈴代紗弓"
        ],
        "大臣": [
          "斧アツシ"
        ],
        "女商人": [
          "上坂すみれ"
        ],
        "女戦士": [
          "葉山いくみ"
        ],
        "女神官": [
          "小倉唯"
        ],
        "女給": [
          "関根明良"
        ],
        "女給仕": [
          "古城門志帆"
        ],
        "女騎士": [
          "藤井ゆきよ"
        ],
        "女魔術師": [
          "M・A・O"
        ],
        "妖精弓手": [
          "東山奈央"
        ],
        "宮廷魔術師": [
          "安元洋貴"
        ],
        "少女巫術師": [
          "原田彩楓"
        ],
        "少年斥候": [
          "若山晃久"
        ],
        "少年魔術師": [
          "伊瀬茉莉也"
        ],
        "新米戦士": [
          "前田誠二"
        ],
        "枢機卿": [
          "野島健児"
        ],
        "槍使い": [
          "松岡禎丞"
        ],
        "武闘家": [
          "石上静香"
        ],
        "牛飼娘": [
          "井口裕香"
        ],
        "王妹": [
          "日高里菜"
        ],
        "監督官": [
          "日岡なつみ"
        ],
        "花冠の森姫": [
          "瀬戸麻沙美"
        ],
        "蜥蜴僧侶": [
          "杉田智和"
        ],
        "蟲人僧侶": [
          "武内駿輔"
        ],
        "見習聖女": [
          "伊藤彩沙"
        ],
        "賢者": [
          "井上ほの花"
        ],
        "軽戦士": [
          "竹田海渡"
        ],
        "輝ける兜の森人": [
          "石川界人"
        ],
        "近衛将軍": [
          "利根健太朗"
        ],
        "重戦士": [
          "濱野大輝"
        ],
        "金等級冒険者": [
          "間宮康弘"
        ],
        "鉱人道士": [
          "中村悠一"
        ],
        "銀髪侍女": [
          "Lynn"
        ],
        "魔女": [
          "日笠陽子"
        ]
      }
    },
    {
      "tid": 6889,
      "title": "アニメロサマーライブ2023 -AXEL- powered by Anison Days",
      "last_updated": "2023-12-24T10:52:23+09:00",
      "episodes": null,
      "songs": null,
      "staff": {},
      "cast": {
        "DAY1": [
          "蒼井翔太",
          "櫻川めぐ",
          "三森すずこ"
        ],
        "DAY2": [
          "小泉萌香",
          "進藤あまね",
          "Machico"
        ],
        "DAY3": [
          "雨宮天",
          "芹澤優",
          "東山奈央"
        ]
      }
    },
    {
      "tid": 6864,
      "title": "経験済みなキミと、経験ゼロなオレが、お付き合いする話。",
      "last_updated": "2023-12-24T11:26:19+09:00",
      "episodes": null,
      "songs": [
        {
          "title": "ラブ・ユー・テンダー！",
          "label": "オープニング",
          "words": null,
          "music": null,
          "composer": [
            "UNDER_COVERS"
          ],
          "singer": [
            "内田真礼"
          ],
          "anime": "経験済みなキミと、経験ゼロなオレが、お付き合いする話。"
        },
        {
          "title": "あいことば",
          "label": "エンディング",
          "words": [
            "TKT"
          ],
          "music": [
            "EREN"
          ],
          "composer": null,
          "singer": [
            "AliA"
          ],
          "anime": "経験済みなキミと、経験ゼロなオレが、お付き合いする話。"
        }
      ],
      "staff": {
        "アニメーション制作": [
          "ENGI"
        ],
        "オフライン編集": [
          "小口理菜"
        ],
        "キャラクターデザイン": [
          "伊藤陽祐"
        ],
        "キャラクター原案": [
          "magako"
        ],
        "シリーズ構成": [
          "福田裕子"
        ],
        "原作": [
          "長岡マキ子(ファンタジア文庫)"
        ],
        "撮影監督": [
          "板倉あゆみ",
          "山本雄介"
        ],
        "監督": [
          "大庭秀昭"
        ],
        "美術監督・美術設定": [
          "宮田遥可"
        ],
        "色彩設計": [
          "山上愛子"
        ],
        "製作": [
          "キミゼロ製作委員会(KADOKAWA",
          "サミー",
          "ドコモ・アニメストア",
          "AT-X",
          "ポニーキャニオン",
          "サンテレビジョン)"
        ],
        "音楽": [
          "羽岡佳"
        ],
        "音楽制作": [
          "ポニーキャニオン"
        ],
        "音響制作": [
          "グロービジョン"
        ],
        "音響効果": [
          "風間結花"
        ],
        "音響監督": [
          "高寺たけし"
        ]
      },
      "cast": {
        "KEN": [
          "KUN"
        ],
        "仁志名蓮": [
          "阪口大助"
        ],
        "伊地知祐輔": [
          "落合福嗣"
        ],
        "加島龍斗": [
          "花江夏樹"
        ],
        "山名笑琉": [
          "福原綾香"
        ],
        "白河月愛": [
          "大西沙織"
        ],
        "谷北朱璃": [
          "楠木ともり"
        ],
        "関家柊吾": [
          "前野智昭"
        ],
        "黒瀬海愛": [
          "古賀葵"
        ],
        "黒瀬真生": [
          "岡本信彦"
        ]
      }
    },
    {
      "tid": 6826,
      "title": "ティアムーン帝国物語～断頭台から始まる、姫の転生逆転ストーリー～",
      "last_updated": "2023-12-24T12:08:29+09:00",
      "episodes": null,
      "songs": [
        {
          "title": "ハッピーエンドプリンセス",
          "label": "オープニング",
          "words": null,
          "music": null,
          "composer": [
            "大石昌良",
            "園田健太郎"
          ],
          "singer": [
            "上坂すみれ"
          ],
          "anime": "ティアムーン帝国物語～断頭台から始まる、姫の転生逆転ストーリー～"
        },
        {
          "title": "Queen of the Night",
          "label": "エンディング",
          "words": null,
          "music": null,
          "composer": [
            "河合英嗣"
          ],
          "singer": null,
          "anime": "ティアムーン帝国物語～断頭台から始まる、姫の転生逆転ストーリー～"
        }
      ],
      "staff": {
        "2Dワークス": [
          "チップチューン"
        ],
        "3D監督": [
          "江田恵一(チップチューン)"
        ],
        "アニメーション制作": [
          "SILVER LINK."
        ],
        "キャラクターデザイン・総作画監督": [
          "大塚舞"
        ],
        "サブキャラクターデザイン": [
          "藤井ありさ(チップチューン)"
        ],
        "シリーズ構成": [
          "赤尾でこ"
        ],
        "プロップデザイン": [
          "直木祥子"
        ],
        "原作": [
          "餅月望(TOブックス)"
        ],
        "原作イラスト": [
          "Gilse"
        ],
        "撮影監督": [
          "新谷優子"
        ],
        "監督": [
          "伊部勇志"
        ],
        "編集": [
          "近藤勇二(REAL-T)"
        ],
        "美術監督": [
          "中原英統"
        ],
        "美術設定": [
          "藤瀬智康(チップチューン)"
        ],
        "色彩設計": [
          "山口真奈美"
        ],
        "製作": [
          "ティアムーン帝国物語製作委員会2023(MBS",
          "キングレコード",
          "ムービック",
          "TOブックス",
          "BS11)"
        ],
        "音楽": [
          "藤本コウジ(Sus4 Inc.)"
        ],
        "音楽制作": [
          "キングレコード"
        ],
        "音響制作": [
          "ビットグルーヴプロモーション"
        ],
        "音響監督": [
          "亀山俊樹"
        ]
      },
      "cast": {
        "アベル・レムノ": [
          "松岡禎丞"
        ],
        "アンヌ・リトシュタイン": [
          "楠木ともり"
        ],
        "キースウッド": [
          "増田俊樹"
        ],
        "ギロちん": [
          "長谷川玲奈"
        ],
        "クロエ・フォークロード": [
          "高橋李依"
        ],
        "シオン・ソール・サンクランド": [
          "堀江瞬"
        ],
        "ティオーナ・ルドルフォン": [
          "高尾奏音"
        ],
        "ディオン・アライア": [
          "古川慎"
        ],
        "ナレーション": [
          "成田剣"
        ],
        "ミーア・ルーナ・ティアムーン": [
          "上坂すみれ"
        ],
        "ラフィーナ・オルカ・ヴェールガ": [
          "東山奈央"
        ],
        "リオラ・ルールー": [
          "斎藤楓子"
        ],
        "ルードヴィッヒ・ヒューイット": [
          "梅原裕一郎"
        ]
      }
    }
  ]
}
